nemui/__init__.py
nemui/nemui.py
nemui-0.0.1.dist-info/METADATA
nemui-0.0.1.dist-info/WHEEL
nemui-0.0.1.dist-info/top_level.txt
nemui-0.0.1.dist-info/RECORD
