Metadata-Version: 2.1
Name: nemui
Version: 0.0.1
Summary: とりあえず作ったパッケージ
Home-page: UNKNOWN
Author: UNKNOWN
Author-email: UNKNOWN
License: UNKNOWN
Platform: UNKNOWN
